echovault/__about__.py
echovault/__init__.py
echovault/app.py
echovault/app.tcss
echovault_cli-0.0.2.dist-info/METADATA
echovault_cli-0.0.2.dist-info/WHEEL
echovault_cli-0.0.2.dist-info/entry_points.txt
echovault_cli-0.0.2.dist-info/licenses/LICENSE.txt
echovault_cli-0.0.2.dist-info/RECORD
